solidity_parser/__init__.py
solidity_parser/__main__.py
solidity_parser/parser.py
solidity_parser/__pycache__/parser.cpython-37.pyc
solidity_parser/solidity_antlr4/SolidityLexer.py
solidity_parser/solidity_antlr4/SolidityListener.py
solidity_parser/solidity_antlr4/SolidityParser.py
solidity_parser/solidity_antlr4/SolidityVisitor.py
solidity_parser/solidity_antlr4/__init__.py
solidity_parser-0.0.7.dist-info/METADATA
solidity_parser-0.0.7.dist-info/WHEEL
solidity_parser-0.0.7.dist-info/top_level.txt
solidity_parser-0.0.7.dist-info/RECORD
