Metadata-Version: 2.1
Name: solidity-parser
Version: 0.0.7
Summary: A Solidity parser for Python built on top of a robust ANTLR4 grammar
Home-page: https://github.com/consensys/python-solidity-parser/
Author: tintinweb
Author-email: tintinweb@oststrom.com
License: MIT
Download-URL: https://github.com/consensys/python-solidity-parser/tarball/v0.0.7
Keywords: solidity,parser,antlr
Platform: UNKNOWN
Requires-Dist: antlr4-python3-runtime
